pylint_per_file_ignores/__init__.py
pylint_per_file_ignores/_plugin.py
pylint_per_file_ignores/py.typed
pylint_per_file_ignores-3.1.0.dist-info/licenses/LICENSE
pylint_per_file_ignores-3.1.0.dist-info/METADATA
pylint_per_file_ignores-3.1.0.dist-info/WHEEL
pylint_per_file_ignores-3.1.0.dist-info/top_level.txt
pylint_per_file_ignores-3.1.0.dist-info/RECORD
