Metadata-Version: 2.4
Name: pylint-per-file-ignores
Version: 3.1.0
Summary: A pylint plugin to ignore error codes per file.
Author-email: Christopher Pickering <christopher@going.bg>, Kai Harder <kai.harder@sap.com>
Maintainer-email: Kai Harder <kai.harder@sap.com>
License-Expression: MIT
Keywords: pylint,plugin,quality,linter
Classifier: Development Status :: 5 - Production/Stable
Classifier: Environment :: Plugins
Classifier: Intended Audience :: Developers
Classifier: Natural Language :: English
Classifier: Operating System :: OS Independent
Classifier: Programming Language :: Python :: 3
Classifier: Programming Language :: Python :: 3 :: Only
Classifier: Programming Language :: Python :: 3.10
Classifier: Programming Language :: Python :: 3.11
Classifier: Programming Language :: Python :: 3.12
Classifier: Programming Language :: Python :: 3.13
Classifier: Programming Language :: Python :: 3.14
Classifier: Topic :: Software Development :: Quality Assurance
Classifier: Typing :: Typed
Requires-Python: <4,>=3.10
License-File: LICENSE
Requires-Dist: pylint<5,>=3.3
Dynamic: license-file
